ishi/VERSION
ishi/__init__.py
ishi/ishi.py
ishi/rules/non_volition_adverb_repnames.txt
ishi/rules/non_volition_head_repnames.txt
ishi/rules/non_volition_semantic_labels.txt
ishi/rules/non_volition_types.txt
ishi/rules/non_volition_verbal_suffix_repnames.txt
ishi/rules/non_volition_verbal_suffix_semantic_labels.txt
ishi/rules/non_volition_voices.txt
ishi/rules/valid_adjective_predicate_suffix_repnames.txt
ishi/rules/valid_nominative_semantic_markers.txt
ishi/rules/valid_nominative_strings.txt
ishi/rules/volition_adverb_repnames.txt
ishi/rules/volition_modalities.txt
ishi/rules/volition_voices.txt
tests/__init__.py
tests/test_cases.py
tests/test_ishi.py
ishi-0.0.3.dist-info/LICENSE
ishi-0.0.3.dist-info/METADATA
ishi-0.0.3.dist-info/WHEEL
ishi-0.0.3.dist-info/top_level.txt
ishi-0.0.3.dist-info/RECORD
