Metadata-Version: 2.1
Name: ishi
Version: 0.0.3
Summary: A volition classifier for Japanese
Home-page: https://github.com/ku-nlp/ishi
Author: Hirokazu Kiyomaru
Author-email: kiyomaru@nlp.ist.i.kyoto-u.ac.jp
License: MIT
Keywords: NLP,Japanese
Platform: UNKNOWN
Classifier: License :: OSI Approved :: MIT License
Classifier: Programming Language :: Python :: 3
Classifier: Programming Language :: Python :: 3.6
Classifier: Programming Language :: Python :: 3.7
Requires-Python: >=3.6
Requires-Dist: pyknp
Requires-Dist: mojimoji
